wrap_torch2jax/__init__.py
wrap_torch2jax/api.py
wrap_torch2jax/compat.py
wrap_torch2jax/compile.py
wrap_torch2jax/dlpack_passing.py
wrap_torch2jax/gradients.py
wrap_torch2jax/utils.py
wrap_torch2jax/cpp/common.cpp
wrap_torch2jax/cpp/cpu_impl.cpp
wrap_torch2jax/cpp/cpu_impl.h
wrap_torch2jax/cpp/gpu_impl.cu
wrap_torch2jax/cpp/gpu_impl.h
wrap_torch2jax/cpp/main.cpp
wrap_torch2jax/cpp/main.cu
wrap_torch2jax/cpp/main.h
wrap_torch2jax-0.7.0.dist-info/METADATA
wrap_torch2jax-0.7.0.dist-info/WHEEL
wrap_torch2jax-0.7.0.dist-info/top_level.txt
wrap_torch2jax-0.7.0.dist-info/RECORD
