Metadata-Version: 2.4
Name: wrap_torch2jax
Version: 0.7.0
Summary: Wrap your PyTorch for JAX! This package allows no-copy PyTorch calling from JAX under both eager execution and JIT.
Author-email: Robert Dyro <robert.dyro@gmail.com>
Project-URL: Homepage, https://github.com/rdyro/torch2jax
Project-URL: Bug Tracker, https://github.com/rdyro/torch2jax
Classifier: Programming Language :: Python :: 3
Classifier: License :: OSI Approved :: MIT License
Classifier: Operating System :: OS Independent
Requires-Python: >=3.7
Requires-Dist: numpy
Requires-Dist: jax
Requires-Dist: torch
Provides-Extra: docs
Requires-Dist: mkdocs; extra == "docs"
Requires-Dist: mkdocs-material; extra == "docs"
Requires-Dist: mkdocstrings[python]; extra == "docs"
Requires-Dist: pymdown-extensions; extra == "docs"
Requires-Dist: mdx_truly_sane_lists; extra == "docs"
